nornir_pyxl/__init__.py
nornir_pyxl/plugins/__init__.py
nornir_pyxl/plugins/tasks/__init__.py
nornir_pyxl/plugins/tasks/helpers.py
nornir_pyxl/plugins/tasks/pyxl_data_map.py
nornir_pyxl/plugins/tasks/pyxl_ez_data.py
nornir_pyxl-1.0.1.dist-info/WHEEL
nornir_pyxl-1.0.1.dist-info/METADATA
nornir_pyxl-1.0.1.dist-info/RECORD
