Metadata-Version: 2.1
Name: nornir-pyxl
Version: 1.0.1
Summary: OpenPyxl plugin for Nornir
Home-page: https://github.com/h4ndzdatm0ld/nornir_pyxl
Keywords: nornir,open_pyxl,pyxl
Author: Hugo
Author-email: hugotinoco@icloud.com
Requires-Python: >=3.8,<4.0
Classifier: Programming Language :: Python :: 3
Classifier: Programming Language :: Python :: 3.8
Classifier: Programming Language :: Python :: 3.9
Requires-Dist: nornir (>=3.0.0,<4.0.0)
Requires-Dist: openpyxl (>=3.0.5,<4.0.0)
Project-URL: Repository, https://github.com/h4ndzdatm0ld/nornir_pyxl
